sentiment_analysis_model/VERSION
sentiment_analysis_model/__init__.py
sentiment_analysis_model/config.yml
sentiment_analysis_model/pipeline.py
sentiment_analysis_model/predict.py
sentiment_analysis_model/train_pipeline.py
sentiment_analysis_model/config/__init__.py
sentiment_analysis_model/config/core.py
sentiment_analysis_model/processing/__init__.py
sentiment_analysis_model/processing/data_manager.py
sentiment_analysis_model/processing/features.py
sentiment_analysis_model/processing/validation.py
sentiment_analysis_model/trained_models/titanic_model_output_v0.0.17.pkl
sentiment_analysis_model-0.0.17.dist-info/METADATA
sentiment_analysis_model-0.0.17.dist-info/WHEEL
sentiment_analysis_model-0.0.17.dist-info/top_level.txt
sentiment_analysis_model-0.0.17.dist-info/RECORD
