Metadata-Version: 2.1
Name: sentiment_analysis_model
Version: 0.0.17
Requires-Dist: pandas
Requires-Dist: numpy
Requires-Dist: scikit-learn
Requires-Dist: pydantic
Requires-Dist: strictyaml
Requires-Dist: joblib
Requires-Dist: nltk
